times/__init__.py
times/version.py
times-0.6.2.dist-info/DESCRIPTION.rst
times-0.6.2.dist-info/METADATA
times-0.6.2.dist-info/pydist.json
times-0.6.2.dist-info/RECORD
times-0.6.2.dist-info/top_level.txt
times-0.6.2.dist-info/WHEEL
